stratdev/__init__.py
stratdev/new_session.py
stratdev/backtesting/analysis.py
stratdev/backtesting/bt.py
stratdev/backtesting/bt_file_content.py
stratdev/backtesting/run_backtest.py
stratdev/utilities/customize.py
stratdev/utilities/file_utils.py
stratdev/utilities/get_utils.py
stratdev-1.0.3.dist-info/METADATA
stratdev-1.0.3.dist-info/WHEEL
stratdev-1.0.3.dist-info/entry_points.txt
stratdev-1.0.3.dist-info/licenses/LICENSE
stratdev-1.0.3.dist-info/RECORD
